kafkalo/__init__.py
kafkalo/cli.py
kafkalo/cli_schema.py
kafkalo/clients.py
kafkalo/config.py
kafkalo/inputparser.py
kafkalo/report.py
kafkalo/schemas.py
kafkalo/topics.py
kafkalo/templates/text.tmpl
kafkalo-0.1.0.dist-info/AUTHORS.rst
kafkalo-0.1.0.dist-info/LICENSE
kafkalo-0.1.0.dist-info/METADATA
kafkalo-0.1.0.dist-info/WHEEL
kafkalo-0.1.0.dist-info/entry_points.txt
kafkalo-0.1.0.dist-info/top_level.txt
kafkalo-0.1.0.dist-info/RECORD
