Metadata-Version: 2.1
Name: kafkalo
Version: 0.1.0
Summary: Manage Kafka topics, schemas and permissions
Home-page: https://github.com/kmetaxas/kafkalo
Author: Konstantinos Metaxas
Author-email: kmetaxas@gmail.com
License: GNU General Public License v3
Keywords: kafkalo
Platform: UNKNOWN
Classifier: Development Status :: 2 - Pre-Alpha
Classifier: Intended Audience :: Developers
Classifier: License :: OSI Approved :: GNU General Public License v3 (GPLv3)
Classifier: Natural Language :: English
Classifier: Programming Language :: Python :: 3
Classifier: Programming Language :: Python :: 3.5
Classifier: Programming Language :: Python :: 3.6
Classifier: Programming Language :: Python :: 3.7
Classifier: Programming Language :: Python :: 3.8
Requires-Python: >=3.5
Requires-Dist: Click (>=7.0)
Requires-Dist: requests (>=2.0)
Requires-Dist: pyyaml
Requires-Dist: environs
Requires-Dist: jinja2
Requires-Dist: confluent-kafka[avro,json,protobuf,schema-registry]
